{"date":"02.07.2014","bank":"PB","baseCurrency":980,"baseCurrencyLit":"UAH","exchangeRate":[{"baseCurrency":"UAH","currency":"AUD","saleRateNB":11.186933,"purchaseRateNB":11.186933},{"baseCurrency":"UAH","currency":"CAD","saleRateNB":11.104107,"purchaseRateNB":11.104107,"saleRate":12,"purchaseRate":10},{"baseCurrency":"UAH","currency":"CZK","saleRateNB":0.590441,"purchaseRateNB":0.590441,"saleRate":0.7,"purchaseRate":0.5},{"baseCurrency":"UAH","currency":"DKK","saleRateNB":2.172507,"purchaseRateNB":2.172507},{"baseCurrency":"UAH","currency":"HUF","saleRateNB":0.0521778,"purchaseRateNB":0.0521778},{"baseCurrency":"UAH","currency":"ILS","saleRateNB":3.450259,"purchaseRateNB":3.450259,"saleRate":4,"purchaseRate":3},{"baseCurrency":"UAH","currency":"JPY","saleRateNB":0.116546,"purchaseRateNB":0.116546,"saleRate":0.15,"purchaseRate":0.09},{"baseCurrency":"UAH","currency":"LVL","saleRateNB":0.116546,"purchaseRateNB":0.116546},{"baseCurrency":"UAH","currency":"LTL","saleRateNB":4.691138,"purchaseRateNB":4.691138},{"baseCurrency":"UAH","currency":"NOK","saleRateNB":1.919597,"purchaseRateNB":1.919597,"saleRate":2.7,"purchaseRate":1.7},{"baseCurrency":"UAH","currency":"SKK","saleRateNB":1.919597,"purchaseRateNB":1.919597},{"baseCurrency":"UAH","currency":"SEK","saleRateNB":1.768293,"purchaseRateNB":1.768293},{"baseCurrency":"UAH","currency":"CHF","saleRateNB":13.344505,"purchaseRateNB":13.344505,"saleRate":14,"purchaseRate":12},{"baseCurrency":"UAH","currency":"RUB","saleRateNB":0.34573,"purchaseRateNB":0.34573,"saleRate":0.37,"purchaseRate":0.325},{"baseCurrency":"UAH","currency":"GBP","saleRateNB":20.295152,"purchaseRateNB":20.295152,"saleRate":21.5,"purchaseRate":19},{"baseCurrency":"UAH","currency":"USD","saleRateNB":11.833402,"purchaseRateNB":11.833402,"saleRate":11.98,"purchaseRate":11.6},{"baseCurrency":"UAH","currency":"BYR","saleRateNB":0.00116,"purchaseRateNB":0.00116},{"baseCurrency":"UAH","currency":"EUR","saleRateNB":16.197561,"purchaseRateNB":16.197561,"saleRate":16.8,"purchaseRate":15.8},{"baseCurrency":"UAH","currency":"GEL","saleRateNB":6.681744,"purchaseRateNB":6.681744},{"baseCurrency":"UAH","currency":"PLZ","saleRateNB":3.89533,"purchaseRateNB":3.89533,"saleRate":4.5,"purchaseRate":3.5}]}