{"date":"07.08.2013","bank":"PB","baseCurrency":980,"baseCurrencyLit":"UAH","exchangeRate":[{"baseCurrency":"UAH","currency":"CAD","saleRateNB":7.704096,"purchaseRateNB":7.704096,"saleRate":8.1,"purchaseRate":7.6},{"baseCurrency":"UAH","currency":"CZK","saleRateNB":0.409518,"purchaseRateNB":0.409518,"saleRate":0.43,"purchaseRate":0.38},{"baseCurrency":"UAH","currency":"HUF","saleRateNB":0.0354237,"purchaseRateNB":0.0354237},{"baseCurrency":"UAH","currency":"ILS","saleRateNB":2.230937,"purchaseRateNB":2.230937,"saleRate":2.4,"purchaseRate":2},{"baseCurrency":"UAH","currency":"JPY","saleRateNB":0.0814823,"purchaseRateNB":0.0814823,"saleRate":0.1,"purchaseRate":0.06},{"baseCurrency":"UAH","currency":"NOK","saleRateNB":1.350299,"purchaseRateNB":1.350299,"saleRate":1.5,"purchaseRate":1.2},{"baseCurrency":"UAH","currency":"SKK","saleRateNB":0.360335,"purchaseRateNB":0.360335},{"baseCurrency":"UAH","currency":"SEK","saleRateNB":1.218512,"purchaseRateNB":1.218512},{"baseCurrency":"UAH","currency":"CHF","saleRateNB":8.620729,"purchaseRateNB":8.620729,"saleRate":8.9,"purchaseRate":8.6},{"baseCurrency":"UAH","currency":"RUB","saleRateNB":0.24266,"purchaseRateNB":0.24266,"saleRate":0.247,"purchaseRate":0.242},{"baseCurrency":"UAH","currency":"GBP","saleRateNB":12.260703,"purchaseRateNB":12.260703,"saleRate":12.6,"purchaseRate":12.2},{"baseCurrency":"UAH","currency":"USD","saleRateNB":7.993,"purchaseRateNB":7.993,"saleRate":8.14,"purchaseRate":8.1},{"baseCurrency":"UAH","currency":"EUR","saleRateNB":10.614704,"purchaseRateNB":10.614704,"saleRate":10.87,"purchaseRate":10.67},{"baseCurrency":"UAH","currency":"GEL","saleRateNB":4.832235,"purchaseRateNB":4.832235},{"baseCurrency":"UAH","currency":"PLZ","saleRateNB":2.518675,"purchaseRateNB":2.518675,"saleRate":2.6,"purchaseRate":2.4}]}