{"date":"08.02.2017","bank":"PB","baseCurrency":980,"baseCurrencyLit":"UAH","exchangeRate":[{"baseCurrency":"UAH","currency":"AUD","saleRateNB":20.591228,"purchaseRateNB":20.591228},{"baseCurrency":"UAH","currency":"CAD","saleRateNB":20.506358,"purchaseRateNB":20.506358},{"baseCurrency":"UAH","currency":"CZK","saleRateNB":1.06793,"purchaseRateNB":1.06793,"saleRate":1.15,"purchaseRate":1},{"baseCurrency":"UAH","currency":"DKK","saleRateNB":3.88102,"purchaseRateNB":3.88102},{"baseCurrency":"UAH","currency":"HUF","saleRateNB":0.0931728,"purchaseRateNB":0.0931728},{"baseCurrency":"UAH","currency":"ILS","saleRateNB":7.198839,"purchaseRateNB":7.198839,"saleRate":7.5,"purchaseRate":6.5},{"baseCurrency":"UAH","currency":"JPY","saleRateNB":0.2405915,"purchaseRateNB":0.2405915,"saleRate":0.25,"purchaseRate":0.21},{"baseCurrency":"UAH","currency":"LVL","saleRateNB":0.2405915,"purchaseRateNB":0.2405915},{"baseCurrency":"UAH","currency":"LTL","saleRateNB":0.2405915,"purchaseRateNB":0.2405915},{"baseCurrency":"UAH","currency":"NOK","saleRateNB":3.248221,"purchaseRateNB":3.248221,"saleRate":3.5,"purchaseRate":3},{"baseCurrency":"UAH","currency":"SKK","saleRateNB":3.248221,"purchaseRateNB":3.248221},{"baseCurrency":"UAH","currency":"SEK","saleRateNB":3.043618,"purchaseRateNB":3.043618},{"baseCurrency":"UAH","currency":"CHF","saleRateNB":27.075011,"purchaseRateNB":27.075011,"saleRate":28,"purchaseRate":25},{"baseCurrency":"UAH","currency":"RUB","saleRateNB":0.45667,"purchaseRateNB":0.45667,"saleRate":0.48,"purchaseRate":0.44},{"baseCurrency":"UAH","currency":"GBP","saleRateNB":33.425862,"purchaseRateNB":33.425862,"saleRate":35,"purchaseRate":31},{"baseCurrency":"UAH","currency":"USD","saleRateNB":27.031894,"purchaseRateNB":27.031894,"saleRate":27.7,"purchaseRate":27.3},{"baseCurrency":"UAH","currency":"BYR","saleRateNB":27.031894,"purchaseRateNB":27.031894},{"baseCurrency":"UAH","currency":"EUR","saleRateNB":28.856547,"purchaseRateNB":28.856547,"saleRate":29.6,"purchaseRate":29.2},{"baseCurrency":"UAH","currency":"GEL","saleRateNB":10.000936,"purchaseRateNB":10.000936},{"baseCurrency":"UAH","currency":"PLZ","saleRateNB":6.705367,"purchaseRateNB":6.705367,"saleRate":7,"purchaseRate":6}]}