{"date":"11.07.2012","bank":"PB","baseCurrency":980,"baseCurrencyLit":"UAH","exchangeRate":[{"baseCurrency":"UAH","currency":"CAD","saleRateNB":7.849241,"purchaseRateNB":7.849241,"saleRate":8.4,"purchaseRate":7.4},{"baseCurrency":"UAH","currency":"CZK","saleRateNB":0.386119,"purchaseRateNB":0.386119,"saleRate":0.44,"purchaseRate":0.34},{"baseCurrency":"UAH","currency":"HUF","saleRateNB":0.0340809,"purchaseRateNB":0.0340809},{"baseCurrency":"UAH","currency":"ILS","saleRateNB":2.039527,"purchaseRateNB":2.039527,"saleRate":2.5,"purchaseRate":1.7},{"baseCurrency":"UAH","currency":"JPY","saleRateNB":0.1005674,"purchaseRateNB":0.1005674,"saleRate":0.12,"purchaseRate":0.07},{"baseCurrency":"UAH","currency":"NOK","saleRateNB":1.311614,"purchaseRateNB":1.311614,"saleRate":1.7,"purchaseRate":1},{"baseCurrency":"UAH","currency":"SKK","saleRateNB":0.360335,"purchaseRateNB":0.360335},{"baseCurrency":"UAH","currency":"SEK","saleRateNB":1.145333,"purchaseRateNB":1.145333},{"baseCurrency":"UAH","currency":"CHF","saleRateNB":8.17602,"purchaseRateNB":8.17602,"saleRate":8.43,"purchaseRate":8.1},{"baseCurrency":"UAH","currency":"RUB","saleRateNB":0.24239,"purchaseRateNB":0.24239,"saleRate":0.25,"purchaseRate":0.24},{"baseCurrency":"UAH","currency":"GBP","saleRateNB":12.396668,"purchaseRateNB":12.396668,"saleRate":13.1,"purchaseRate":12.1},{"baseCurrency":"UAH","currency":"USD","saleRateNB":7.993,"purchaseRateNB":7.993,"saleRate":8.14,"purchaseRate":8.09},{"baseCurrency":"UAH","currency":"EUR","saleRateNB":9.819401,"purchaseRateNB":9.819401,"saleRate":10.1,"purchaseRate":9.77},{"baseCurrency":"UAH","currency":"PLZ","saleRateNB":2.338955,"purchaseRateNB":2.338955,"saleRate":2.6,"purchaseRate":2}]}