{"date":"12.12.2012","bank":"PB","baseCurrency":980,"baseCurrencyLit":"UAH","exchangeRate":[{"baseCurrency":"UAH","currency":"CAD","saleRateNB":8.100862,"purchaseRateNB":8.100862,"saleRate":8.6,"purchaseRate":7.6},{"baseCurrency":"UAH","currency":"CZK","saleRateNB":0.410649,"purchaseRateNB":0.410649,"saleRate":0.46,"purchaseRate":0.36},{"baseCurrency":"UAH","currency":"HUF","saleRateNB":0.036809,"purchaseRateNB":0.036809},{"baseCurrency":"UAH","currency":"ILS","saleRateNB":2.076913,"purchaseRateNB":2.076913,"saleRate":2.5,"purchaseRate":1.7},{"baseCurrency":"UAH","currency":"JPY","saleRateNB":0.0969592,"purchaseRateNB":0.0969592,"saleRate":0.12,"purchaseRate":0.07},{"baseCurrency":"UAH","currency":"NOK","saleRateNB":1.415374,"purchaseRateNB":1.415374,"saleRate":1.7,"purchaseRate":1},{"baseCurrency":"UAH","currency":"SKK","saleRateNB":0.360335,"purchaseRateNB":0.360335},{"baseCurrency":"UAH","currency":"SEK","saleRateNB":1.201322,"purchaseRateNB":1.201322},{"baseCurrency":"UAH","currency":"CHF","saleRateNB":8.57227,"purchaseRateNB":8.57227,"saleRate":9.25,"purchaseRate":8.25},{"baseCurrency":"UAH","currency":"RUB","saleRateNB":0.25993,"purchaseRateNB":0.25993,"saleRate":0.27,"purchaseRate":0.26},{"baseCurrency":"UAH","currency":"GBP","saleRateNB":12.862652,"purchaseRateNB":12.862652,"saleRate":13.65,"purchaseRate":12.65},{"baseCurrency":"UAH","currency":"USD","saleRateNB":7.993,"purchaseRateNB":7.993,"saleRate":8.165,"purchaseRate":8.11},{"baseCurrency":"UAH","currency":"EUR","saleRateNB":10.385305,"purchaseRateNB":10.385305,"saleRate":10.7,"purchaseRate":10.4},{"baseCurrency":"UAH","currency":"GEL","saleRateNB":4.825234,"purchaseRateNB":4.825234},{"baseCurrency":"UAH","currency":"PLZ","saleRateNB":2.537891,"purchaseRateNB":2.537891,"saleRate":2.8,"purchaseRate":2.2}]}