{"date":"20.10.2014","bank":"PB","baseCurrency":980,"baseCurrencyLit":"UAH","exchangeRate":[{"baseCurrency":"UAH","currency":"AUD","saleRateNB":11.377187,"purchaseRateNB":11.377187},{"baseCurrency":"UAH","currency":"CAD","saleRateNB":11.520033,"purchaseRateNB":11.520033,"saleRate":13,"purchaseRate":11.8},{"baseCurrency":"UAH","currency":"CZK","saleRateNB":0.604077,"purchaseRateNB":0.604077,"saleRate":0.65,"purchaseRate":0.55},{"baseCurrency":"UAH","currency":"DKK","saleRateNB":2.230363,"purchaseRateNB":2.230363},{"baseCurrency":"UAH","currency":"HUF","saleRateNB":0.054025,"purchaseRateNB":0.054025},{"baseCurrency":"UAH","currency":"ILS","saleRateNB":3.514693,"purchaseRateNB":3.514693,"saleRate":4,"purchaseRate":3.4},{"baseCurrency":"UAH","currency":"JPY","saleRateNB":0.1217096,"purchaseRateNB":0.1217096,"saleRate":0.14,"purchaseRate":0.11},{"baseCurrency":"UAH","currency":"LVL","saleRateNB":0.1217096,"purchaseRateNB":0.1217096},{"baseCurrency":"UAH","currency":"LTL","saleRateNB":4.809801,"purchaseRateNB":4.809801},{"baseCurrency":"UAH","currency":"NOK","saleRateNB":1.981421,"purchaseRateNB":1.981421,"saleRate":2.5,"purchaseRate":1.9},{"baseCurrency":"UAH","currency":"SKK","saleRateNB":1.981421,"purchaseRateNB":1.981421},{"baseCurrency":"UAH","currency":"SEK","saleRateNB":1.814369,"purchaseRateNB":1.814369},{"baseCurrency":"UAH","currency":"CHF","saleRateNB":13.75458,"purchaseRateNB":13.75458,"saleRate":14.7,"purchaseRate":13.5},{"baseCurrency":"UAH","currency":"RUB","saleRateNB":0.31554,"purchaseRateNB":0.31554,"saleRate":0.33,"purchaseRate":0.315},{"baseCurrency":"UAH","currency":"GBP","saleRateNB":20.876531,"purchaseRateNB":20.876531,"saleRate":22,"purchaseRate":20.5},{"baseCurrency":"UAH","currency":"USD","saleRateNB":12.951166,"purchaseRateNB":12.951166,"saleRate":13.02,"purchaseRate":12.9},{"baseCurrency":"UAH","currency":"BYR","saleRateNB":0.00121,"purchaseRateNB":0.00121},{"baseCurrency":"UAH","currency":"EUR","saleRateNB":16.60728,"purchaseRateNB":16.60728,"saleRate":16.6,"purchaseRate":16.4},{"baseCurrency":"UAH","currency":"GEL","saleRateNB":7.3894,"purchaseRateNB":7.3894},{"baseCurrency":"UAH","currency":"PLZ","saleRateNB":3.924401,"purchaseRateNB":3.924401,"saleRate":4.3,"purchaseRate":3.8}]}