{"date":"21.09.2015","bank":"PB","baseCurrency":980,"baseCurrencyLit":"UAH","exchangeRate":[{"baseCurrency":"UAH","currency":"DKK","saleRateNB":3.311802,"purchaseRateNB":3.311802},{"baseCurrency":"UAH","currency":"HUF","saleRateNB":0.0797586,"purchaseRateNB":0.0797586},{"baseCurrency":"UAH","currency":"ILS","saleRateNB":5.555662,"purchaseRateNB":5.555662,"saleRate":6.1,"purchaseRate":5.5},{"baseCurrency":"UAH","currency":"JPY","saleRateNB":0.1812781,"purchaseRateNB":0.1812781,"saleRate":0.2,"purchaseRate":0.18},{"baseCurrency":"UAH","currency":"LVL","saleRateNB":0.1812781,"purchaseRateNB":0.1812781},{"baseCurrency":"UAH","currency":"LTL","saleRateNB":5.570235,"purchaseRateNB":5.570235},{"baseCurrency":"UAH","currency":"NOK","saleRateNB":2.675113,"purchaseRateNB":2.675113,"saleRate":3,"purchaseRate":2.6},{"baseCurrency":"UAH","currency":"SKK","saleRateNB":2.675113,"purchaseRateNB":2.675113},{"baseCurrency":"UAH","currency":"SEK","saleRateNB":2.649925,"purchaseRateNB":2.649925},{"baseCurrency":"UAH","currency":"CHF","saleRateNB":22.642739,"purchaseRateNB":22.642739,"saleRate":24.3,"purchaseRate":23.3},{"baseCurrency":"UAH","currency":"RUB","saleRateNB":0.32965,"purchaseRateNB":0.32965,"saleRate":0.36,"purchaseRate":0.33},{"baseCurrency":"UAH","currency":"GBP","saleRateNB":33.85862,"purchaseRateNB":33.85862,"saleRate":36,"purchaseRate":34},{"baseCurrency":"UAH","currency":"USD","saleRateNB":21.639391,"purchaseRateNB":21.639391,"saleRate":23.2,"purchaseRate":21.2},{"baseCurrency":"UAH","currency":"BYR","saleRateNB":0.00123,"purchaseRateNB":0.00123},{"baseCurrency":"UAH","currency":"EUR","saleRateNB":24.710021,"purchaseRateNB":24.710021,"saleRate":26.5,"purchaseRate":25.5},{"baseCurrency":"UAH","currency":"GEL","saleRateNB":9.281666,"purchaseRateNB":9.281666},{"baseCurrency":"UAH","currency":"PLZ","saleRateNB":5.879139,"purchaseRateNB":5.879139,"saleRate":6.4,"purchaseRate":5.8},{"baseCurrency":"UAH","currency":"AUD","saleRateNB":15.72985,"purchaseRateNB":15.72985},{"baseCurrency":"UAH","currency":"CAD","saleRateNB":16.610662,"purchaseRateNB":16.610662,"saleRate":17.8,"purchaseRate":16.8},{"baseCurrency":"UAH","currency":"CZK","saleRateNB":0.912786,"purchaseRateNB":0.912786,"saleRate":1,"purchaseRate":0.9}]}