{"date":"25.09.2013","bank":"PB","baseCurrency":980,"baseCurrencyLit":"UAH","exchangeRate":[{"baseCurrency":"UAH","currency":"AUD","saleRateNB":7.506077,"purchaseRateNB":7.506077},{"baseCurrency":"UAH","currency":"CAD","saleRateNB":7.771501,"purchaseRateNB":7.771501,"saleRate":8.2,"purchaseRate":7.7},{"baseCurrency":"UAH","currency":"CZK","saleRateNB":0.415261,"purchaseRateNB":0.415261,"saleRate":0.43,"purchaseRate":0.38},{"baseCurrency":"UAH","currency":"DKK","saleRateNB":1.444123,"purchaseRateNB":1.444123},{"baseCurrency":"UAH","currency":"HUF","saleRateNB":0.0359097,"purchaseRateNB":0.0359097},{"baseCurrency":"UAH","currency":"ILS","saleRateNB":2.184775,"purchaseRateNB":2.184775,"saleRate":2.4,"purchaseRate":2},{"baseCurrency":"UAH","currency":"JPY","saleRateNB":0.0810184,"purchaseRateNB":0.0810184,"saleRate":0.1,"purchaseRate":0.06},{"baseCurrency":"UAH","currency":"LVL","saleRateNB":15.327311,"purchaseRateNB":15.327311},{"baseCurrency":"UAH","currency":"LTL","saleRateNB":3.118909,"purchaseRateNB":3.118909},{"baseCurrency":"UAH","currency":"NOK","saleRateNB":1.342764,"purchaseRateNB":1.342764,"saleRate":1.5,"purchaseRate":1.2},{"baseCurrency":"UAH","currency":"SKK","saleRateNB":0.360335,"purchaseRateNB":0.360335},{"baseCurrency":"UAH","currency":"SEK","saleRateNB":1.247636,"purchaseRateNB":1.247636},{"baseCurrency":"UAH","currency":"CHF","saleRateNB":8.75882,"purchaseRateNB":8.75882,"saleRate":9.1,"purchaseRate":8.8},{"baseCurrency":"UAH","currency":"RUB","saleRateNB":0.25122,"purchaseRateNB":0.25122,"saleRate":0.26,"purchaseRate":0.253},{"baseCurrency":"UAH","currency":"GBP","saleRateNB":12.754757,"purchaseRateNB":12.754757,"saleRate":13.25,"purchaseRate":12.95},{"baseCurrency":"UAH","currency":"USD","saleRateNB":7.993,"purchaseRateNB":7.993,"saleRate":8.19,"purchaseRate":8.17},{"baseCurrency":"UAH","currency":"BYR","saleRateNB":0.00088,"purchaseRateNB":0.00088},{"baseCurrency":"UAH","currency":"EUR","saleRateNB":10.768969,"purchaseRateNB":10.768969,"saleRate":11.15,"purchaseRate":10.88},{"baseCurrency":"UAH","currency":"GEL","saleRateNB":4.811003,"purchaseRateNB":4.811003},{"baseCurrency":"UAH","currency":"PLZ","saleRateNB":2.547723,"purchaseRateNB":2.547723,"saleRate":2.8,"purchaseRate":2.45}]}