{"date":"27.07.2012","bank":"PB","baseCurrency":980,"baseCurrencyLit":"UAH","exchangeRate":[{"baseCurrency":"UAH","currency":"CAD","saleRateNB":7.930898,"purchaseRateNB":7.930898,"saleRate":8.5,"purchaseRate":7.5},{"baseCurrency":"UAH","currency":"CZK","saleRateNB":0.384216,"purchaseRateNB":0.384216,"saleRate":0.43,"purchaseRate":0.33},{"baseCurrency":"UAH","currency":"HUF","saleRateNB":0.0344069,"purchaseRateNB":0.0344069},{"baseCurrency":"UAH","currency":"ILS","saleRateNB":2.039527,"purchaseRateNB":2.039527,"saleRate":2.5,"purchaseRate":1.7},{"baseCurrency":"UAH","currency":"JPY","saleRateNB":0.1023011,"purchaseRateNB":0.1023011,"saleRate":0.12,"purchaseRate":0.07},{"baseCurrency":"UAH","currency":"NOK","saleRateNB":1.324425,"purchaseRateNB":1.324425,"saleRate":1.7,"purchaseRate":1},{"baseCurrency":"UAH","currency":"SKK","saleRateNB":0.360335,"purchaseRateNB":0.360335},{"baseCurrency":"UAH","currency":"SEK","saleRateNB":1.159626,"purchaseRateNB":1.159626},{"baseCurrency":"UAH","currency":"CHF","saleRateNB":8.159382,"purchaseRateNB":8.159382,"saleRate":8.42,"purchaseRate":8.1},{"baseCurrency":"UAH","currency":"RUB","saleRateNB":0.24502,"purchaseRateNB":0.24502,"saleRate":0.253,"purchaseRate":0.243},{"baseCurrency":"UAH","currency":"GBP","saleRateNB":12.518418,"purchaseRateNB":12.518418,"saleRate":13.2,"purchaseRate":12.2},{"baseCurrency":"UAH","currency":"USD","saleRateNB":7.993,"purchaseRateNB":7.993,"saleRate":8.125,"purchaseRate":8.08},{"baseCurrency":"UAH","currency":"EUR","saleRateNB":9.799418,"purchaseRateNB":9.799418,"saleRate":10.05,"purchaseRate":9.75},{"baseCurrency":"UAH","currency":"GEL","saleRateNB":4.879128,"purchaseRateNB":4.879128},{"baseCurrency":"UAH","currency":"PLZ","saleRateNB":2.360964,"purchaseRateNB":2.360964,"saleRate":2.6,"purchaseRate":2}]}