{"date":"27.07.2017","bank":"PB","baseCurrency":980,"baseCurrencyLit":"UAH","exchangeRate":[{"baseCurrency":"UAH","currency":"AUD","saleRateNB":20.479942,"purchaseRateNB":20.479942},{"baseCurrency":"UAH","currency":"CAD","saleRateNB":20.678054,"purchaseRateNB":20.678054},{"baseCurrency":"UAH","currency":"CZK","saleRateNB":1.157152,"purchaseRateNB":1.157152,"saleRate":1.17,"purchaseRate":1.07},{"baseCurrency":"UAH","currency":"DKK","saleRateNB":4.052863,"purchaseRateNB":4.052863},{"baseCurrency":"UAH","currency":"HUF","saleRateNB":0.0986364,"purchaseRateNB":0.0986364},{"baseCurrency":"UAH","currency":"ILS","saleRateNB":7.250675,"purchaseRateNB":7.250675,"saleRate":7.5,"purchaseRate":6.5},{"baseCurrency":"UAH","currency":"JPY","saleRateNB":0.2313859,"purchaseRateNB":0.2313859,"saleRate":0.25,"purchaseRate":0.21},{"baseCurrency":"UAH","currency":"LVL","saleRateNB":0.2313859,"purchaseRateNB":0.2313859},{"baseCurrency":"UAH","currency":"LTL","saleRateNB":0.2313859,"purchaseRateNB":0.2313859},{"baseCurrency":"UAH","currency":"NOK","saleRateNB":3.244629,"purchaseRateNB":3.244629,"saleRate":3.4,"purchaseRate":2.9},{"baseCurrency":"UAH","currency":"SKK","saleRateNB":3.244629,"purchaseRateNB":3.244629},{"baseCurrency":"UAH","currency":"SEK","saleRateNB":3.149295,"purchaseRateNB":3.149295},{"baseCurrency":"UAH","currency":"CHF","saleRateNB":27.026839,"purchaseRateNB":27.026839,"saleRate":28,"purchaseRate":25},{"baseCurrency":"UAH","currency":"RUB","saleRateNB":0.43206,"purchaseRateNB":0.43206,"saleRate":0.46,"purchaseRate":0.42},{"baseCurrency":"UAH","currency":"GBP","saleRateNB":33.761222,"purchaseRateNB":33.761222,"saleRate":35,"purchaseRate":31},{"baseCurrency":"UAH","currency":"USD","saleRateNB":25.88486,"purchaseRateNB":25.88486,"saleRate":26,"purchaseRate":25.7},{"baseCurrency":"UAH","currency":"BYR","saleRateNB":25.88486,"purchaseRateNB":25.88486},{"baseCurrency":"UAH","currency":"EUR","saleRateNB":30.140331,"purchaseRateNB":30.140331,"saleRate":30.5,"purchaseRate":29.9},{"baseCurrency":"UAH","currency":"GEL","saleRateNB":10.826829,"purchaseRateNB":10.826829},{"baseCurrency":"UAH","currency":"PLZ","saleRateNB":7.073037,"purchaseRateNB":7.073037,"saleRate":7.2,"purchaseRate":6.3}]}