{"date":"30.05.2012","bank":"PB","baseCurrency":980,"baseCurrencyLit":"UAH","exchangeRate":[{"baseCurrency":"UAH","currency":"CAD","saleRateNB":7.798214,"purchaseRateNB":7.798214,"saleRate":8.1,"purchaseRate":7.1},{"baseCurrency":"UAH","currency":"CZK","saleRateNB":0.392325,"purchaseRateNB":0.392325,"saleRate":0.44,"purchaseRate":0.34},{"baseCurrency":"UAH","currency":"HUF","saleRateNB":0.0335985,"purchaseRateNB":0.0335985},{"baseCurrency":"UAH","currency":"ILS","saleRateNB":2.126161,"purchaseRateNB":2.126161,"saleRate":2.5,"purchaseRate":1.7},{"baseCurrency":"UAH","currency":"JPY","saleRateNB":0.1004517,"purchaseRateNB":0.1004517,"saleRate":0.12,"purchaseRate":0.07},{"baseCurrency":"UAH","currency":"NOK","saleRateNB":1.330897,"purchaseRateNB":1.330897,"saleRate":1.7,"purchaseRate":1},{"baseCurrency":"UAH","currency":"SKK","saleRateNB":0.360335,"purchaseRateNB":0.360335},{"baseCurrency":"UAH","currency":"SEK","saleRateNB":1.113783,"purchaseRateNB":1.113783},{"baseCurrency":"UAH","currency":"CHF","saleRateNB":8.330427,"purchaseRateNB":8.330427,"saleRate":8.47,"purchaseRate":8.14},{"baseCurrency":"UAH","currency":"RUB","saleRateNB":0.2491,"purchaseRateNB":0.2491,"saleRate":0.254,"purchaseRate":0.244},{"baseCurrency":"UAH","currency":"GBP","saleRateNB":12.52065,"purchaseRateNB":12.52065,"saleRate":13.1,"purchaseRate":12.1},{"baseCurrency":"UAH","currency":"USD","saleRateNB":7.9925,"purchaseRateNB":7.9925,"saleRate":8.105,"purchaseRate":8.06},{"baseCurrency":"UAH","currency":"EUR","saleRateNB":10.009008,"purchaseRateNB":10.009008,"saleRate":10.15,"purchaseRate":9.9},{"baseCurrency":"UAH","currency":"PLZ","saleRateNB":2.295118,"purchaseRateNB":2.295118,"saleRate":2.7,"purchaseRate":1.7}]}